trelent_data_ingestion_sdk/__init__.py
trelent_data_ingestion_sdk/client.py
trelent_data_ingestion_sdk/config.py
trelent_data_ingestion_sdk/fragment.py
trelent_data_ingestion_sdk/models.py
data_ingestion_sdk-0.4.13.dist-info/METADATA
data_ingestion_sdk-0.4.13.dist-info/WHEEL
data_ingestion_sdk-0.4.13.dist-info/top_level.txt
data_ingestion_sdk-0.4.13.dist-info/RECORD
