Metadata-Version: 2.4
Name: data-ingestion-sdk
Version: 0.4.13
Summary: Python SDK for the Data Ingestion API
Requires-Python: >=3.12
Requires-Dist: pydantic<3,>=2.11.0
Requires-Dist: requests<3,>=2.31.0
Requires-Dist: typing-extensions>=4.8.0
